receiptsplitter.py
receiptsplitter-0.0.1.dist-info/LICENSE
receiptsplitter-0.0.1.dist-info/METADATA
receiptsplitter-0.0.1.dist-info/WHEEL
receiptsplitter-0.0.1.dist-info/entry_points.txt
receiptsplitter-0.0.1.dist-info/top_level.txt
receiptsplitter-0.0.1.dist-info/RECORD
