Metadata-Version: 2.1
Name: receiptsplitter
Version: 0.0.1
Summary: App for splitting the cost on a receipt
Author: Elli Greaves
License: BSD-3-Clause-Clear license
Project-URL: Homepage, https://github.com/Grvs44/receiptsplitter
Classifier: Programming Language :: Python :: 3
Classifier: License :: OSI Approved :: BSD License
Classifier: Operating System :: OS Independent
Requires-Python: <4,>=3.10
License-File: LICENSE
